{
  "ID": "63110a30-bb13-4254-9de4-0d3bd1d66bfb",
  "payment": {
    "paymentStartOptions": [
      {
        "type": "START_OF_RENT",
        "isEnabled": true
      },
      {
        "type": "START_OF_MONTH",
        "isEnabled": true
      }
    ],
    "paymentTypeOptions": [
      {
        "type": "TWO_PAYMENTS",
        "priceAffect": 2000,
        "isEnabled": true
      },
      {
        "type": "ONE_PAYMENT",
        "priceAffect": 0,
        "isEnabled": true
      }
    ],
    "penalty": null
  },
  "paymentContent": {
    "paymentTypeOnePayment": "Одним платежом",
    "paymentTypeTwoPayments": "Двумя платежами за дополнительные 2000 руб. в месяц к сумме аренды",
    "paymentType": "Тип оплаты: Двумя платежами",
    "penalty": "В случае задержки оплаты оплата не взимается",
    "paymentRules": "оплата за первый месяц найма в полном объеме"
  },
  "address": {
    "house": "д. 56",
    "flat": "кв. 222",
    "street": "улица Свободы",
    "city": "г. Москва"
  },
  "meta": {
    "propertyType": "Тип жилья: Однокомнатная"
  },
  "options": [
    {
      "title": "Электричество",
      "isEnabled": false
    },
    {
      "title": "Кондиционер",
      "isEnabled": true
    },
    {
      "title": "Телевизор",
      "isEnabled": true
    },
    {
      "title": "Интернет",
      "isEnabled": false
    }
  ],
  "optionsContent": {
    "title": "Опции: ",
    "option": "кондиционер; телевизор"
  },
  "termsContent": [
    {
      "title": "Условия аренды",
      "periodUnit": "дней",
      "rentalPeriod": "Период аренды: __1__ (от 1 до 3) дней",
      "pricePerMonth": "100000 руб.",
      "deposit": "100000 руб.",
      "depositCollectType": "При заезде: Без депозита, каждый месяц стоит дороже на 10000 руб.",
      "depositCollectTypeOptions": [
        {
          "type": "ABSENT_WITH_EXTRA_CHARGE",
          "priceAffect": "10000",
          "isEnabled": true,
          "label": "При заезде: Без депозита, каждый месяц стоит дороже на 10000 руб."
        },
        {
          "type": "PARTIAL",
          "priceAffect": "2000",
          "isEnabled": true,
          "label": "При заезде: депозит частями: 2 раза в месяц"
        }
      ],
      "depositReturnType": "В случае разрыва контракта: Стоимость месяца пересчитывается",
      "depositReturnPeriod": "в течение 0 календарных undefined",
      "terminationRules": "найм на период 3 месяцев и менее по 145000 руб. в месяц; найм на период 6 месяцев и менее по 150000 руб. в месяц",
      "ID": "98bd5647-acfc-4dd3-979b-71bcf2d765e9"
    },
    {
      "title": "Условия аренды",
      "periodUnit": "месяцев",
      "rentalPeriod": "Период аренды: __3__ (от 3 до 6) месяцев",
      "pricePerMonth": "90000 руб.",
      "deposit": "100000 руб.",
      "depositCollectType": "При заезде: депозит частями: 2 раза в месяц",
      "depositCollectTypeOptions": [
        {
          "type": "ABSENT_WITH_EXTRA_CHARGE",
          "priceAffect": 0,
          "isEnabled": false,
          "label": "При заезде: Без депозита, каждый месяц стоит дороже на 0 руб."
        },
        {
          "type": "PARTIAL",
          "priceAffect": "2000",
          "isEnabled": true,
          "label": "При заезде: депозит частями: 2 раза в месяц"
        }
      ],
      "depositReturnType": "В случае разрыва контракта: Стоимость месяца пересчитывается",
      "depositReturnPeriod": "в течение 0 календарных undefined",
      "terminationRules": "найм на период 3 месяцев и менее по 160000 руб. в месяц; найм на период 6 месяцев и менее по 140000 руб. в месяц; найм на период 9 месяцев и менее по 120000 руб. в месяц",
      "ID": "9ae9bc31-98d2-44b6-8cc9-83423e8b80ec"
    },
    {
      "title": "Условия аренды",
      "periodUnit": "месяцев",
      "rentalPeriod": "Период аренды: __6__ (от 6 до 12) месяцев",
      "pricePerMonth": "90000 руб.",
      "deposit": "100000 руб.",
      "depositCollectType": "При заезде: Оплата депозита сразу",
      "depositCollectTypeOptions": [
        {
          "type": "ABSENT_WITH_EXTRA_CHARGE",
          "priceAffect": 0,
          "isEnabled": false,
          "label": "При заезде: Без депозита, каждый месяц стоит дороже на 0 руб."
        },
        {
          "type": "PARTIAL",
          "priceAffect": 0,
          "isEnabled": false,
          "label": "При заезде: депозит частями: 2 раза в месяц"
        }
      ],
      "depositReturnType": "В случае разрыва контракта: Стоимость месяца пересчитывается",
      "depositReturnPeriod": "в течение 0 календарных undefined",
      "terminationRules": "найм на период 6 месяцев и менее по 110000 руб. в месяц",
      "ID": "e6f4b97f-237f-494a-83a8-01051edf31f2"
    }
  ],
  "terms": [
    {
      "deposit": {
        "returnPeriod": 0,
        "isEnabled": true,
        "returnPeriodUnit": "",
        "value": 100000,
        "returnType": "RECALCULATE_PRICE",
        "collectOptions": [
          {
            "type": "ABSENT_WITH_EXTRA_CHARGE",
            "priceAffect": "10000",
            "isEnabled": true
          },
          {
            "type": "PARTIAL",
            "priceAffect": "2000",
            "isEnabled": true
          }
        ]
      },
      "periodFrom": 1,
      "periodTo": 3,
      "periodUnit": "days",
      "price": 100000,
      "priceUnit": "RUB",
      "terminationRules": [
        {
          "props": {
            "currency": "RUB",
            "period": 3,
            "periodUnit": "months",
            "value": 145000
          }
        },
        {
          "props": {
            "currency": "RUB",
            "period": 6,
            "periodUnit": "months",
            "value": 150000
          }
        }
      ],
      "ID": "98bd5647-acfc-4dd3-979b-71bcf2d765e9"
    },
    {
      "deposit": {
        "returnPeriod": 0,
        "isEnabled": true,
        "returnPeriodUnit": "",
        "value": 100000,
        "returnType": "RECALCULATE_PRICE",
        "collectOptions": [
          {
            "type": "ABSENT_WITH_EXTRA_CHARGE",
            "priceAffect": 0,
            "isEnabled": false
          },
          {
            "type": "PARTIAL",
            "priceAffect": "2000",
            "isEnabled": true
          }
        ]
      },
      "periodFrom": 3,
      "periodTo": 6,
      "periodUnit": "months",
      "price": 90000,
      "priceUnit": "RUB",
      "terminationRules": [
        {
          "props": {
            "currency": "RUB",
            "period": 3,
            "periodUnit": "months",
            "value": 160000
          }
        },
        {
          "props": {
            "currency": "RUB",
            "period": 6,
            "periodUnit": "months",
            "value": 140000
          }
        },
        {
          "props": {
            "currency": "RUB",
            "period": 9,
            "periodUnit": "months",
            "value": 120000
          }
        }
      ],
      "ID": "9ae9bc31-98d2-44b6-8cc9-83423e8b80ec"
    },
    {
      "deposit": {
        "returnPeriod": 0,
        "isEnabled": true,
        "returnPeriodUnit": "",
        "value": 100000,
        "returnType": "RECALCULATE_PRICE",
        "collectOptions": [
          {
            "type": "ABSENT_WITH_EXTRA_CHARGE",
            "priceAffect": 0,
            "isEnabled": false
          },
          {
            "type": "PARTIAL",
            "priceAffect": 0,
            "isEnabled": false
          }
        ]
      },
      "periodFrom": 6,
      "periodTo": 12,
      "periodUnit": "months",
      "price": 90000,
      "priceUnit": "RUB",
      "terminationRules": [
        {
          "props": {
            "currency": "RUB",
            "period": 6,
            "periodUnit": "months",
            "value": 110000
          }
        }
      ],
      "ID": "e6f4b97f-237f-494a-83a8-01051edf31f2"
    }
  ]
}
